ctyunsdk_vpc20220909/__init__.py
ctyunsdk_vpc20220909/vpc_client.py
ctyunsdk_vpc20220909/models/__init__.py
ctyunsdk_vpc20220909/models/openapi_v4_acl_update.py
ctyunsdk_vpc20220909/models/v4_acl_clone.py
ctyunsdk_vpc20220909/models/v4_acl_create.py
ctyunsdk_vpc20220909/models/v4_acl_delete.py
ctyunsdk_vpc20220909/models/v4_acl_list.py
ctyunsdk_vpc20220909/models/v4_acl_new_list.py
ctyunsdk_vpc20220909/models/v4_acl_query.py
ctyunsdk_vpc20220909/models/v4_acl_rule_create.py
ctyunsdk_vpc20220909/models/v4_acl_rule_delete.py
ctyunsdk_vpc20220909/models/v4_acl_rule_list.py
ctyunsdk_vpc20220909/models/v4_acl_rule_update.py
ctyunsdk_vpc20220909/models/v4_ports_assign_ipv6.py
ctyunsdk_vpc20220909/models/v4_ports_assign_secondary_private_ips.py
ctyunsdk_vpc20220909/models/v4_ports_async_attach_bm.py
ctyunsdk_vpc20220909/models/v4_ports_async_detach_bm.py
ctyunsdk_vpc20220909/models/v4_ports_attach.py
ctyunsdk_vpc20220909/models/v4_ports_batch_assign_ipv6.py
ctyunsdk_vpc20220909/models/v4_ports_batch_unassign_ipv6.py
ctyunsdk_vpc20220909/models/v4_ports_change_private_ip.py
ctyunsdk_vpc20220909/models/v4_ports_change_vpc.py
ctyunsdk_vpc20220909/models/v4_ports_check_status.py
ctyunsdk_vpc20220909/models/v4_ports_check_status_batch.py
ctyunsdk_vpc20220909/models/v4_ports_create.py
ctyunsdk_vpc20220909/models/v4_ports_delete.py
ctyunsdk_vpc20220909/models/v4_ports_detach.py
ctyunsdk_vpc20220909/models/v4_ports_list.py
ctyunsdk_vpc20220909/models/v4_ports_new_list.py
ctyunsdk_vpc20220909/models/v4_ports_show.py
ctyunsdk_vpc20220909/models/v4_ports_unassign_ipv6.py
ctyunsdk_vpc20220909/models/v4_ports_unassign_secondary_private_ips.py
ctyunsdk_vpc20220909/models/v4_ports_update.py
ctyunsdk_vpc20220909/models/v4_vpc_associate_secondary_cidrs.py
ctyunsdk_vpc20220909/models/v4_vpc_batch_attach_security_group_ports.py
ctyunsdk_vpc20220909/models/v4_vpc_batch_detach_security_group_ports.py
ctyunsdk_vpc20220909/models/v4_vpc_batch_join_security_group.py
ctyunsdk_vpc20220909-2.0.1.dist-info/licenses/LICENSE.txt
ctyunsdk_vpc20220909-2.0.1.dist-info/METADATA
ctyunsdk_vpc20220909-2.0.1.dist-info/WHEEL
ctyunsdk_vpc20220909-2.0.1.dist-info/top_level.txt
ctyunsdk_vpc20220909-2.0.1.dist-info/RECORD
