Metadata-Version: 2.4
Name: ctyunsdk_vpc20220909
Version: 2.0.1
Author-email: Ctyun Cloud SDK <ctyunsdk@chinatelecom.cn>
License: MIT
Project-URL: Homepage, https://github.com/ctyunsdk/ctyun-python-sdk
Project-URL: Repository, https://github.com/ctyunsdk/ctyun-python-sdk
Classifier: Programming Language :: Python :: 3
Classifier: License :: OSI Approved :: MIT License
Classifier: Operating System :: OS Independent
Requires-Python: >=3.9
License-File: LICENSE.txt
Requires-Dist: requests>=2.32.5
Requires-Dist: ctyun_python_sdk_core>=0.0.1
Dynamic: license-file
